CHANGES.txt
MANIFEST.in
README.txt
setup.py
pysourcesearch/__init__.py
pysourcesearch/catalog.py
pysourcesearch/configure.zcml
pysourcesearch/models.py
pysourcesearch/run.py
pysourcesearch/settings.py
pysourcesearch/tests.py
pysourcesearch/views.py
pysourcesearch.egg-info/PKG-INFO
pysourcesearch.egg-info/SOURCES.txt
pysourcesearch.egg-info/dependency_links.txt
pysourcesearch.egg-info/entry_points.txt
pysourcesearch.egg-info/not-zip-safe
pysourcesearch.egg-info/requires.txt
pysourcesearch.egg-info/top_level.txt
pysourcesearch/templates/search.pt
pysourcesearch/templates/view.pt
pysourcesearch/templates/static/default.css
pysourcesearch/templates/static/templatelicense.txt
pysourcesearch/templates/static/images/img01.gif
pysourcesearch/templates/static/images/img02.gif
pysourcesearch/templates/static/images/img03.gif
pysourcesearch/templates/static/images/img04.gif
pysourcesearch/templates/static/images/spacer.gif