Metadata-Version: 1.0
Name: pysourcesearch
Version: 0.1
Summary: a repoze.bfg wsgi app to provide a search engine for your python packages
Home-page: UNKNOWN
Author: Nathan Van Gheem
Author-email: vangheem@gmail.com
License: UNKNOWN
Keywords: web wsgi bfg catalog python source search
Platform: UNKNOWN
Classifier: Programming Language :: Python
Classifier: Framework :: BFG
Classifier: Topic :: Internet :: WWW/HTTP
Classifier: Topic :: Internet :: WWW/HTTP :: WSGI :: Application
